{
    "nodes":[
        {
            "mac":[
                "52:54:00:38:a1:62"
            ],
            "cpu":"4",
            "memory":"20480",
            "disk":"45",
            "name":"A-0",
            "arch":"x86_64",
            "pm_user": "SECRET",
            "pm_addr": "192.168.24.1",
            "pm_password": "SECRET",
            "pm_port": "6230",
            "pm_type": "pxe_ipmitool"
          },
          {
            "mac":[
                "52:54:00:50:1a:a4"
            ],
            "cpu":"4",
            "memory":"20480",
            "disk":"45",
            "name":"A-1",
            "arch":"x86_64",
            "pm_user": "SECRET",
            "pm_addr": "192.168.24.1",
            "pm_password": "SECRET",
            "pm_port": "6231",
            "pm_type": "pxe_ipmitool"
          },
          {
            "mac":[
                "52:54:00:32:7a:2a"
            ],
            "cpu":"4",
            "memory":"20480",
            "disk":"45",
            "name":"A-2",
            "arch":"x86_64",
            "pm_user": "SECRET",
            "pm_addr": "192.168.24.1",
            "pm_password": "SECRET",
            "pm_port": "6232",
            "pm_type": "pxe_ipmitool"
          },
          {
            "mac":[
                "52:54:00:47:7e:5a"
            ],
            "cpu":"6",
            "memory":"30720",
            "disk":"45",
            "name":"C-0",
            "arch":"x86_64",
            "pm_user": "SECRET",
            "pm_addr": "192.168.24.1",
            "pm_password": "SECRET",
            "pm_port": "6250",
            "pm_type": "pxe_ipmitool"
          },
          {
            "mac":[
                "52:54:00:6e:01:05"
            ],
            "cpu":"6",
            "memory":"30720",
            "disk":"45",
            "name":"C-1",
            "arch":"x86_64",
            "pm_user": "SECRET",
            "pm_addr": "192.168.24.1",
            "pm_password": "SECRET",
            "pm_port": "6251",
            "pm_type": "pxe_ipmitool"
          },
          {
            "mac":[
                "52:54:00:29:96:c0"
            ],
            "cpu":"6",
            "memory":"30720",
            "disk":"45",
            "name":"C-2",
            "arch":"x86_64",
            "pm_user": "SECRET",
            "pm_addr": "192.168.24.1",
            "pm_password": "SECRET",
            "pm_port": "6252",
            "pm_type": "pxe_ipmitool"
          }
      ]
}
